{
  "$schema": "https://developer.microsoft.com/json-schemas/fabric/item/report/definition/page/2.1.0/schema.json",
  "name": "97cdea23de21d802bb6b",
  "displayName": "Operations Overview",
  "displayOption": "FitToPage",
  "height": 720,
  "width": 1280,
  "objects": {
    "outspace": [
      {
        "properties": {
          "transparency": {
            "expr": {
              "Literal": {
                "Value": "50D"
              }
            }
          },
          "color": {
            "solid": {
              "color": {
                "expr": {
                  "ThemeDataColor": {
                    "ColorId": 0,
                    "Percent": -0.1
                  }
                }
              }
            }
          }
        }
      }
    ],
    "outspacePane": [
      {
        "properties": {
          "width": {
            "expr": {
              "Literal": {
                "Value": "237L"
              }
            }
          }
        }
      }
    ]
  },
  "visualInteractions": [
    {
      "source": "a88c7825a260d2871ff2",
      "target": "d8bb9ff73900eace02e9",
      "type": "DataFilter"
    },
    {
      "source": "950011acc2e7061061ad",
      "target": "d8bb9ff73900eace02e9",
      "type": "DataFilter"
    }
  ]
}